Image_stitching.py
main.py
copymanga_dl-3.2.dist-info/LICENSE
copymanga_dl-3.2.dist-info/METADATA
copymanga_dl-3.2.dist-info/WHEEL
copymanga_dl-3.2.dist-info/entry_points.txt
copymanga_dl-3.2.dist-info/RECORD
