Metadata-Version: 2.1
Name: copymanga-dl
Version: 3.2
Summary: Copymanga Downloader
Home-page: https://misaka.sakurakoi.top/
License: GPL-3.0-or-later
Keywords: copymanga,downloader
Author: misaka10843
Author-email: misaka10843@outlook.jp
Requires-Python: >=3.10,<4
Classifier: License :: OSI Approved :: GNU General Public License v3 or later (GPLv3+)
Classifier: Operating System :: MacOS
Classifier: Operating System :: Microsoft :: Windows
Classifier: Programming Language :: Python :: 3
Classifier: Programming Language :: Python :: 3.10
Classifier: Programming Language :: Python :: 3.11
Classifier: Programming Language :: Python :: 3.10
Classifier: Programming Language :: Python :: 3.11
Classifier: Topic :: Internet :: WWW/HTTP
Classifier: Topic :: Utilities
Requires-Dist: requests (>=2.28.2)
Requires-Dist: retrying (>=1.3.4)
Requires-Dist: rich (>=13.3.2)
Project-URL: Repository, https://github.com/misaka10843/copymanga-downloader
